[
  {
    "level": "stx B",
    "termDate": "20210526",
    "year": "2021",
    "author": "UVM",
    "licens": "STUK",
    "testformat": "UDEN",
    "points": "10",
    "questionnumber": "1",
    "category": "Vektorer og analytisk geometri",
    "questiontext": "Bestem koordinatsættet til punktet på linjen, når \\( t=2 \\).\n Angiv en retningsvektor for linjen.\n En ret linje er bestemt ved paramterfremstillingen \\[ \\binom{x}{y} = \\binom{6}{0} + t \\cdot \\binom{3}{4}. \\]",
    "pictureurl": "null"
  },
  {
    "level": "stx B",
    "termDate": "20210526",
    "year": "2021",
    "author": "UVM",
    "licens": "STUK",
    "testformat": "UDEN",
    "points": "10",
    "questionnumber": "2",
    "category": "Kombinatorik og sandsynlighedsfelter",
    "questiontext": "Bestem antallet af måder, hvorpå man kan danne udvalget.\n En bestyrelse består af 8 medlemmer. Der skal vælges 3 personer blandt bestyrelsens medlemmer til et udvalg.",
    "pictureurl": "null"
  },
  {
    "level": "stx B",
    "termDate": "20210526",
    "year": "2021",
    "author": "UVM",
    "licens": "STUK",
    "testformat": "UDEN",
    "points": "10",
    "questionnumber": "3",
    "category": "Andengradspolynomier",
    "questiontext": "Tegn parablen.\n Bestem førstekoordinaten til toppunktet \\( T \\) for parablen.\n En parabel er bestem ved ligningen \\[ y=x^2-4x+5. \\]",
    "pictureurl": "null"
  },
  {
    "level": "stx B",
    "termDate": "20210526",
    "year": "2021",
    "author": "UVM",
    "licens": "STUK",
    "testformat": "UDEN",
    "points": "10",
    "questionnumber": "4",
    "category": "Reduktioner, ligninger og formler",
    "questiontext": "Reducér udtrykket \\[ (a-b)^2+2a\\cdot b \\]",
    "pictureurl": "null"
  },
  {
    "level": "stx B",
    "termDate": "20210526",
    "year": "2021",
    "author": "UVM",
    "licens": "STUK",
    "testformat": "UDEN",
    "points": "10",
    "questionnumber": "5",
    "category": "Differentialregning",
    "questiontext": "Bestem monotoniforholdende for \\( f \\).\n Bestem \\( f'(x) \\).\n En funktion \\( f \\) er givet ved \\[ f(x) = \\frac{1}{3}x^3-2x^2+3x+1. \\]",
    "pictureurl": "null"
  },
  {
    "level": "stx B",
    "termDate": "20210526",
    "year": "2021",
    "author": "UVM",
    "licens": "STUK",
    "testformat": "MED",
    "points": "10",
    "questionnumber": "6",
    "category": "Differentialregning",
    "questiontext": "Bestem maksimum for \\( f \\).\n Tegn grafen for \\( f \\).\n En funktion \\( f \\) er givet ved \\[ f(x) = 0.5 \\cdot x \\cdot \\sqrt{144-x^2}, 0\\leq x \\leq 12. \\]",
    "pictureurl": "null"
  },
  {
    "level": "stx B",
    "termDate": "20210526",
    "year": "2021",
    "author": "UVM",
    "licens": "STUK",
    "testformat": "MED",
    "points": "10",
    "questionnumber": "7",
    "category": "Vektorer og analytisk geometri",
    "questiontext": "Bestem den spidse vinkel mellem $l$ og $m$.\n Bestem koordinatsættet til skæringspunktet mellem $l$ og $m$.\n \\[ m: -x+2y=4 \\]\n \\[ l: 2x+3y=-1 \\]\n Linjerne $l$ og $m$ er givet ved ligningerne",
    "pictureurl": "null"
  },
  {
    "level": "stx B",
    "termDate": "20210526",
    "year": "2021",
    "author": "UVM",
    "licens": "STUK",
    "testformat": "MED",
    "points": "10",
    "questionnumber": "8",
    "category": "Differentialregning",
    "questiontext": "Bestem væksthastigheden for det årlige antal nedlagte råvildt til tidspunktet $x=40$.\n Benyt modellen til at bestemme det årstal, hvor det årlige antal nedlagte råvildt var 120000.\n hvor $f(x)$ angiver det årlige antal nedlagte råvildt til tispunktet $x$ (målt i antal år efter 1980).\n I en model kan udviklingen i det årlige antal nedlagte råvildt i Danmark beskrives ved \\[ f(x)=\\frac{150000}{1+2.6\\cdot \\mathrm{e}^{-0.1\\cdot x}} ,\\]",
    "pictureurl": "null"
  },
  {
    "level": "stx B",
    "termDate": "20210526",
    "year": "2021",
    "author": "UVM",
    "licens": "STUK",
    "testformat": "MED",
    "points": "10",
    "questionnumber": "9",
    "category": "Regression",
    "questiontext": "Kilde: statistikbanken.dk\n Bestem residualspredningen.\n Bestem tallene $a$ og $b$ ved regression på tabellens data.\n I en model kan udviklingen beskrives ved \\[ f(t) = a\\cdot t +b ,\\] hvor $f(t)$ betegner gennemsnitsalderen (målt i år) til tidspunktet $t$ (målt i antal år efter 2004).\n TABEL\n Tabellen viser udviklingen i gennemsnitsalderen for førstegangsfødende kvinder i Danmark i perioden 2004-2018.",
    "pictureurl": "null"
  },
  {
    "level": "stx B",
    "termDate": "20210526",
    "year": "2021",
    "author": "UVM",
    "licens": "STUK",
    "testformat": "MED",
    "points": "10",
    "questionnumber": "10",
    "category": "Kombinatorik og sandsynlighedsfelter",
    "questiontext": "En person ønsker at undersøge nulhypotesen:\n Bestem middelværdien af \\( X \\).\n Den stokastiske variabel \\( X \\) angiver antallet af stykker mørk chokolade i en julekalender. \\( X \\) er binomialfordelt med antalsparameter \\( n=24 \\) og sandsynlighedsparameter \\( p=\\frac{1}{2} \\).\n En chokoladefabrik påstår, at de producerer lige mange stykker lys og mørk chokolade. Alle chokoladestykkerne fyldes på en tilfældig måde i julekalendere. Hver julekalender indeholder i alt 24 stykker chokolade.\n Benyt et tosidet binomialtest til at undersøge, om man kan forkaste nulhypotesen på et 5% signifikansniveau.\n Personen køber en julekalender fra fabrikken med 24 stykker chokolade, hvoraf 7 er mørk chokolade.\n Chokoladenfabrikken producerer lige mange stykker lys og mørk chokolade, dvs. \\( p=\\frac{1}{2} \\).",
    "pictureurl": "null"
  },
  {
    "level": "stx B",
    "termDate": "20210526",
    "year": "2021",
    "author": "UVM",
    "licens": "STUK",
    "testformat": "MED",
    "points": "10",
    "questionnumber": "11",
    "category": "Vektorer og analytisk geometri",
    "questiontext": "Beskriv linje for linje de omskrivninger eller konklusioner, der er foretaget.\n En omskrivning af cirklens ligning ses nedenfor. \\begin{align*}\r\n1.& &x^2-2x+y^2+2y &=83 \\\\\r\n2.& &x^2-8x+16+y^2+2y+1 &= 83+16+1 \\\\\r\n3.& &(x-4)^2 + (y+1)^2 &= 83+16+1 \\\\\r\n4.& &(x-4)^2 + (y+1)^2 &= 100 \\\\\r\n5.& &C(4,-1) \\text{ og } r &=10 \\\\\r\n\\end{align*}\n Undersøg, om punktet $P(12,5)$ ligger på cirklen.\n En cirkel er givet ved ligningen \\[ x^2 - 8x + y^2 +2y = 83. \\]",
    "pictureurl": "null"
  },
  {
    "level": "stx B vejledende",
    "termDate": "20180601",
    "year": "2018",
    "author": "Opgavekommissionen",
    "licens": "fri",
    "testformat": "UDEN",
    "points": "10",
    "questionnumber": "12",
    "category": "Reduktioner, ligninger og formler",
    "questiontext": "Reducér udtrykket $2q\\cdot (p+q)-p\\cdot (2q+p)$.",
    "pictureurl": "null"
  },
  {
    "level": "stx B vejledende",
    "termDate": "20180601",
    "year": "2018",
    "author": "Opgavekommissionen",
    "licens": "fri",
    "testformat": "UDEN",
    "points": "10",
    "questionnumber": "13",
    "category": "Reduktioner, ligninger og formler",
    "questiontext": "Løs and"
  }]
